napari_clemreg/__init__.py
napari_clemreg/_reader.py
napari_clemreg/napari.yaml
napari_clemreg/_tests/__init__.py
napari_clemreg/_tests/test_dock_widget.py
napari_clemreg/clemreg/data_preprocessing.py
napari_clemreg/clemreg/empanada_segmentation.py
napari_clemreg/clemreg/log_segmentation.py
napari_clemreg/clemreg/mask_roi.py
napari_clemreg/clemreg/on_init_specs.py
napari_clemreg/clemreg/point_cloud_registration.py
napari_clemreg/clemreg/point_cloud_sampling.py
napari_clemreg/clemreg/sample_data.py
napari_clemreg/clemreg/warp_image_volume.py
napari_clemreg/clemreg/widget_components.py
napari_clemreg/empanada_configs/MitoNet_V1.yaml
napari_clemreg/widgets/fixed_segmentation.py
napari_clemreg/widgets/moving_segmentation.py
napari_clemreg/widgets/point_cloud_sampling.py
napari_clemreg/widgets/registration_warping.py
napari_clemreg/widgets/run_registration.py
napari_clemreg-0.2.1.dist-info/LICENSE
napari_clemreg-0.2.1.dist-info/METADATA
napari_clemreg-0.2.1.dist-info/WHEEL
napari_clemreg-0.2.1.dist-info/entry_points.txt
napari_clemreg-0.2.1.dist-info/top_level.txt
napari_clemreg-0.2.1.dist-info/RECORD
