Metadata-Version: 2.1
Name: napari-clemreg
Version: 0.2.1
Summary: A plugin for registering multimodal image volumes based on common segmented structures of interest with point-clouds.
Home-page: https://github.com/krentzd/napari-clemreg
Author: Daniel Krentzel
Author-email: dkrentzel@pm.me
License: MIT
Project-URL: Bug Tracker, https://github.com/krentzd/napari-clemreg/issues
Project-URL: Documentation, https://github.com/krentzd/napari-clemreg#README.md
Project-URL: Source Code, https://github.com/krentzd/napari-clemreg
Project-URL: User Support, https://github.com/krentzd/napari-clemreg/issues
Classifier: Development Status :: 2 - Pre-Alpha
Classifier: Intended Audience :: Developers
Classifier: Framework :: napari
Classifier: Topic :: Software Development :: Testing
Classifier: Programming Language :: Python
Classifier: Programming Language :: Python :: 3
Classifier: Programming Language :: Python :: 3.7
Classifier: Programming Language :: Python :: 3.8
Classifier: Programming Language :: Python :: 3.9
Classifier: Operating System :: OS Independent
Classifier: License :: OSI Approved :: MIT License
Requires-Python: >=3.7
License-File: LICENSE
Requires-Dist: typing_extensions
Requires-Dist: setuptools
Requires-Dist: packaging
Requires-Dist: numpy==1.22.0
Requires-Dist: magicgui==0.7.3
Requires-Dist: scipy==1.10.1
Requires-Dist: napari
Requires-Dist: scikit-image==0.21.0
Requires-Dist: h5py==3.9.0
Requires-Dist: matplotlib==3.7.3
Requires-Dist: imageio==2.31.5
Requires-Dist: tifffile==2023.7.10
Requires-Dist: probreg==0.3.6
Requires-Dist: open3d==0.17.0
Requires-Dist: transforms3d==0.4.1
Requires-Dist: tqdm==4.66.1
Requires-Dist: empanada-dl==0.1.7
Requires-Dist: torch==2.0.1
Requires-Dist: magicgui==0.7.3
Requires-Dist: connected-components-3d==3.12.3
